AUTHORS.txt
CHANGES.txt
LICENSE.txt
MANIFEST.in
README.md
setup.py
lambda_proxy/__init__.py
lambda_proxy/proxy.py
lambda_proxy/templates.py
lambda_proxy.egg-info/PKG-INFO
lambda_proxy.egg-info/SOURCES.txt
lambda_proxy.egg-info/dependency_links.txt
lambda_proxy.egg-info/not-zip-safe
lambda_proxy.egg-info/requires.txt
lambda_proxy.egg-info/top_level.txt