Metadata-Version: 2.1
Name: lambda-proxy
Version: 4.0.0
Summary: Simple AWS Lambda proxy to handle API Gateway request
Home-page: https://github.com/vincentsarago/lambda-proxy
Author: Vincent Sarago
Author-email: vincent.sarago@gmail.com
License: BSD
Keywords: AWS-Lambda API-Gateway Request Proxy
Platform: UNKNOWN
Classifier: Intended Audience :: Information Technology
Classifier: Intended Audience :: Science/Research
Classifier: License :: OSI Approved :: BSD License
Classifier: Programming Language :: Python :: 3.6
Classifier: Programming Language :: Python :: 3.7
Requires-Python: >=3
Provides-Extra: test
